moodle_dl/__init__.py
moodle_dl/config.py
moodle_dl/database.py
moodle_dl/main.py
moodle_dl/types.py
moodle_dl/utils.py
moodle_dl/version.py
moodle_dl/cli/__init__.py
moodle_dl/cli/config_wizard.py
moodle_dl/cli/database_manager.py
moodle_dl/cli/moodle_wizard.py
moodle_dl/cli/notifications_wizard.py
moodle_dl/downloader/__init__.py
moodle_dl/downloader/download_service.py
moodle_dl/downloader/fake_download_service.py
moodle_dl/downloader/task.py
moodle_dl/downloader/extractors/__init__.py
moodle_dl/downloader/extractors/echo360.py
moodle_dl/downloader/extractors/googledrive.py
moodle_dl/downloader/extractors/helixmedia_lti.py
moodle_dl/downloader/extractors/kalvidres_lti.py
moodle_dl/downloader/extractors/opencast_lti.py
moodle_dl/downloader/extractors/owncloud.py
moodle_dl/downloader/extractors/sharepoint.py
moodle_dl/downloader/extractors/sharepointfiles.py
moodle_dl/moodle/__init__.py
moodle_dl/moodle/cookie_handler.py
moodle_dl/moodle/core_handler.py
moodle_dl/moodle/moodle_constants.py
moodle_dl/moodle/moodle_service.py
moodle_dl/moodle/request_helper.py
moodle_dl/moodle/result_builder.py
moodle_dl/moodle/mods/__init__.py
moodle_dl/moodle/mods/assign.py
moodle_dl/moodle/mods/book.py
moodle_dl/moodle/mods/calendar.py
moodle_dl/moodle/mods/common.py
moodle_dl/moodle/mods/data.py
moodle_dl/moodle/mods/folder.py
moodle_dl/moodle/mods/forum.py
moodle_dl/moodle/mods/lesson.py
moodle_dl/moodle/mods/page.py
moodle_dl/moodle/mods/quiz.py
moodle_dl/moodle/mods/workshop.py
moodle_dl/notifications/__init__.py
moodle_dl/notifications/notification_service.py
moodle_dl/notifications/console/__init__.py
moodle_dl/notifications/console/console_service.py
moodle_dl/notifications/discord/__init__.py
moodle_dl/notifications/discord/discord_formatter.py
moodle_dl/notifications/discord/discord_service.py
moodle_dl/notifications/discord/discord_shooter.py
moodle_dl/notifications/mail/__init__.py
moodle_dl/notifications/mail/header.png
moodle_dl/notifications/mail/header_extender.png
moodle_dl-2.3.13.dist-info/AUTHORS
moodle_dl-2.3.13.dist-info/LICENSE
moodle_dl-2.3.13.dist-info/METADATA
moodle_dl-2.3.13.dist-info/WHEEL
moodle_dl-2.3.13.dist-info/entry_points.txt
moodle_dl-2.3.13.dist-info/top_level.txt
moodle_dl-2.3.13.dist-info/RECORD
