Metadata-Version: 2.1
Name: moodle-dl
Version: 2.3.13
Summary: Moodle-DL downloads course content fast from Moodle (eg. lecture pdfs)
Home-page: https://github.com/C0D3D3V/Moodle-DL
Author: C0D3D3V
Author-email: moodle-dl@ist-ein-knaller.de
License: GPL-3.0
Project-URL: Documentation, https://github.com/C0D3D3V/Moodle-DL#readme
Project-URL: Wiki, https://github.com/C0D3D3V/Moodle-DL/wiki
Project-URL: Source, https://github.com/C0D3D3V/Moodle-DL
Project-URL: Tracker, https://github.com/C0D3D3V/Moodle-DL/issues
Classifier: Development Status :: 5 - Production/Stable
Classifier: Environment :: Console
Classifier: Intended Audience :: End Users/Desktop
Classifier: License :: OSI Approved :: GNU General Public License v3 (GPLv3)
Classifier: Programming Language :: Python :: 3 :: Only
Classifier: Topic :: Education
Classifier: Topic :: Internet :: WWW/HTTP :: Indexing/Search
Classifier: Topic :: Multimedia :: Video
Classifier: Topic :: Multimedia :: Sound/Audio
Classifier: Topic :: Utilities
Requires-Python: >=3.7
License-File: LICENSE
License-File: AUTHORS
Requires-Dist: aiodns>=3.0.0
Requires-Dist: aiofiles>=22.1.0
Requires-Dist: aiohttp>=3.8.4
Requires-Dist: certifi>=2020.4.5.2
Requires-Dist: colorama>=0.4.6
Requires-Dist: colorlog>=6.7.0
Requires-Dist: html2text>=2020.1.16
Requires-Dist: readchar>=4.0.3
Requires-Dist: requests>=2.24.0
Requires-Dist: sentry-sdk>=0.13.5
Requires-Dist: xmpppy>=0.7.1
Requires-Dist: yt-dlp>=2024.3.10
